dynamo_io/__init__.py
dynamo_io/_deserializer.py
dynamo_io/_serializer.py
dynamo_io/definitions.py
dynamo_io/mock/__init__.py
dynamo_io/mock/_comparisons.py
dynamo_io/mock/_conditioner.py
dynamo_io/mock/_expressions.py
dynamo_io/mock/_paginators.py
dynamo_io/mock/_tables.py
dynamo_io/reader.py
dynamo_io/recorder/__init__.py
dynamo_io/tests/__init__.py
dynamo_io/tests/fixtures.py
dynamo_io/tests/mock/__init__.py
dynamo_io/tests/mock/expressions/__init__.py
dynamo_io/tests/mock/expressions/test_get_clause.py
dynamo_io/tests/mock/expressions/test_parse_sets.py
dynamo_io/tests/mock/test_formatting.py
dynamo_io/tests/mock/test_mocking.py
dynamo_io/tests/mock/test_mocking_records.py
dynamo_io/tests/reader/__init__.py
dynamo_io/tests/reader/test_get_indexed_record.py
dynamo_io/tests/reader/test_get_record.py
dynamo_io/tests/reader/test_get_records_for_partition.py
dynamo_io/tests/recorder/__init__.py
dynamo_io/tests/recorder/test_deserializer_deserialize.py
dynamo_io/tests/recorder/test_record_class.py
dynamo_io/tests/recorder/test_serializer_serialize.py
dynamo_io/tests/test_io.py
dynamo_io/tests/writer/__init__.py
dynamo_io/tests/writer/test_insert_records.py
dynamo_io/tests/writer/test_transacts.py
dynamo_io/tests/writer/test_upsert.py
dynamo_io/writer.py
dynamo_io-0.2.2.dist-info/WHEEL
dynamo_io-0.2.2.dist-info/METADATA
dynamo_io-0.2.2.dist-info/RECORD
